aironsuit/__init__.py
aironsuit/_utils.py
aironsuit/callbacks.py
aironsuit/suit.py
aironsuit/design/__init__.py
aironsuit/design/model_designers.py
aironsuit/design/utils.py
aironsuit-0.1.20.dist-info/LICENSE
aironsuit-0.1.20.dist-info/METADATA
aironsuit-0.1.20.dist-info/WHEEL
aironsuit-0.1.20.dist-info/top_level.txt
aironsuit-0.1.20.dist-info/RECORD
